{
  "formatted_address": "5000 Ang Mo Kio Ave 5, Singapore 569870",
  "geometry": {
    "location": {
      "lat": 1.3775777,
      "lng": 103.8638825
    },
    "viewport": {
      "northeast": {
        "lat": 1.379137880291502,
        "lng": 103.8651787802915
      },
      "southwest": {
        "lat": 1.376439919708498,
        "lng": 103.8624808197085
      }
    }
  },
  "name": "Almanach (Lamps & Luminaires Pte Ltd)",
  "place_id": "ChIJ0ToMjc8Z2jERjP-SR-TnJpc",
  "types": [
    "home_goods_store",
    "point_of_interest",
    "store",
    "establishment"
  ],
  "url": "https://maps.google.com/?cid=10891647716481499020",
  "vicinity": "5000 Ang Mo Kio Avenue 5"
}