{
  "formatted_address": "Springside Ave, Singapore",
  "geometry": {
    "location": {
      "lat": 1.4056255,
      "lng": 103.8230199
    },
    "viewport": {
      "northeast": {
        "lat": 1.407103230291502,
        "lng": 103.8243449302915
      },
      "southwest": {
        "lat": 1.404405269708498,
        "lng": 103.8216469697085
      }
    }
  },
  "name": "Brook's Park",
  "place_id": "ChIJRUIq3BsV2jERV37UsYnmQJw",
  "rating": 4,
  "reviews": [
    {
      "author_name": "Vidya Pai",
      "author_url": "https://www.google.com/maps/contrib/105823251592083347896/reviews",
      "language": "en",
      "original_language": "en",
      "profile_photo_url": "https://lh3.googleusercontent.com/a/ACg8ocJA-fuzaeUFdoDC-iYEFPqB--mt48fz5RLDYEyhNDnu7xgylQ=s128-c0x00000000-cc-rp-mo-ba3",
      "rating": 1,
      "relative_time_description": "2 years ago",
      "text": "This place is no where close to water.its a very small play area kind of park 🤔 it was a disappointment for us",
      "time": 1659186181,
      "translated": false
    },
    {
      "author_name": "Tan Yoke Chun",
      "author_url": "https://www.google.com/maps/contrib/104526208276545946355/reviews",
      "language": "en",
      "original_language": "en",
      "profile_photo_url": "https://lh3.googleusercontent.com/a-/ALV-UjXorcIE4qGR6qAZHrR1m117DDJnBZolZ7-CqXhGbwXAcAJdC0j1kA=s128-c0x00000000-cc-rp-mo-ba4",
      "rating": 5,
      "relative_time_description": "2 years ago",
      "text": "Natural view great for exploring or leisurely stroll",
      "time": 1657806575,
      "translated": false
    },
    {
      "author_name": "sathiaraj kanagaraj",
      "author_url": "https://www.google.com/maps/contrib/112628041687564546696/reviews",
      "language": "en",
      "original_language": "en",
      "profile_photo_url": "https://lh3.googleusercontent.com/a-/ALV-UjV3FohdadFbQD2a8Z8veER_4fXRhNf4GwFqKuuLscpGRNBCvy4Y=s128-c0x00000000-cc-rp-mo",
      "rating": 5,
      "relative_time_description": "4 years ago",
      "text": "Really I enjoyable...",
      "time": 1596538735,
      "translated": false
    },
    {
      "author_name": "GbpHaoMusic",
      "author_url": "https://www.google.com/maps/contrib/101738617669728191152/reviews",
      "profile_photo_url": "https://lh3.googleusercontent.com/a-/ALV-UjV4XHqGAH13Ep9hF9xCswqOymv7oD2roGqI-q_o84he24-Zu4U=s128-c0x00000000-cc-rp-mo",
      "rating": 5,
      "relative_time_description": "2 years ago",
      "text": "",
      "time": 1678190744,
      "translated": false
    },
    {
      "author_name": "yap hong teo",
      "author_url": "https://www.google.com/maps/contrib/105080463812040191633/reviews",
      "profile_photo_url": "https://lh3.googleusercontent.com/a-/ALV-UjXjrJg19ZJ2mTKPOh_SDO0fn3cODJubLC7ZOgKm6-yKnYpDPvs=s128-c0x00000000-cc-rp-mo-ba3",
      "rating": 5,
      "relative_time_description": "3 years ago",
      "text": "",
      "time": 1630731001,
      "translated": false
    }
  ],
  "types": [
    "park",
    "point_of_interest",
    "establishment"
  ],
  "url": "https://maps.google.com/?cid=11259252547494641239",
  "user_ratings_total": 6,
  "vicinity": "Springside Avenue"
}