{
  "formatted_address": "85 Whampoa Dr, Singapore 320085",
  "geometry": {
    "location": {
      "lat": 1.3228056,
      "lng": 103.8563978
    },
    "viewport": {
      "northeast": {
        "lat": 1.323755130291502,
        "lng": 103.8576233802915
      },
      "southwest": {
        "lat": 1.321057169708498,
        "lng": 103.8549254197085
      }
    }
  },
  "name": "Ntuc Childcare - Whampoa",
  "place_id": "ChIJKyidX9cZ2jERV2ygqztwmFw",
  "types": [
    "school",
    "point_of_interest",
    "establishment"
  ],
  "url": "https://maps.google.com/?cid=6672206249534188631",
  "vicinity": "85 Whampoa Drive"
}