{
  "formatted_address": "30 Pioneer Cres, West-park, Singapore 628560",
  "geometry": {
    "location": {
      "lat": 1.3145454,
      "lng": 103.6954755
    },
    "viewport": {
      "northeast": {
        "lat": 1.315914130291502,
        "lng": 103.6969700302915
      },
      "southwest": {
        "lat": 1.313216169708498,
        "lng": 103.6942720697085
      }
    }
  },
  "name": "VM SOUTH INDIAN FOOD",
  "place_id": "ChIJzYh6P_4F2jERxVgUG_SJyms",
  "rating": 4.7,
  "reviews": [
    {
      "author_name": "Sharan Shastri",
      "author_url": "https://www.google.com/maps/contrib/107486687725907175668/reviews",
      "language": "en",
      "original_language": "en",
      "profile_photo_url": "https://lh3.googleusercontent.com/a-/ALV-UjWxpPBW66QbHBWTfKGORFho-W9kVvhRt_M5uK4bIV4YFhkwXAAr=s128-c0x00000000-cc-rp-mo-ba3",
      "rating": 3,
      "relative_time_description": "a year ago",
      "text": "Good for quick south Indian (veg) breakfast options. Breakfast usually gets over by 9:30 - 10:00 AM. Best to have before then",
      "time": 1710261927,
      "translated": false
    },
    {
      "author_name": "Etsuo Okazaki",
      "author_url": "https://www.google.com/maps/contrib/117454716727999664575/reviews",
      "language": "en",
      "original_language": "en",
      "profile_photo_url": "https://lh3.googleusercontent.com/a/ACg8ocKF2LkmlqIeAHjPq5hkoeTSAa_wl-9iZUuYgt-31nx79LOcKA=s128-c0x00000000-cc-rp-mo",
      "rating": 5,
      "relative_time_description": "2 years ago",
      "text": "The briyani is very nice but sadly it’s close already.\nAny one know where’s its relocated?",
      "time": 1669081781,
      "translated": false
    },
    {
      "author_name": "gerald jacob",
      "author_url": "https://www.google.com/maps/contrib/100001572274250848271/reviews",
      "language": "en",
      "original_language": "en",
      "profile_photo_url": "https://lh3.googleusercontent.com/a-/ALV-UjU2SfTonK8BU3B7znOyCkvOhO0ZRot-AJCskVKH3Dc_nABwzWI2iw=s128-c0x00000000-cc-rp-mo",
      "rating": 5,
      "relative_time_description": "2 years ago",
      "text": "Surprised with quality and the taste.\nI tried the briyani with prawns and another day with the fish.\n\nBoth were good. The briyani was flavourful!",
      "time": 1667979978,
      "translated": false
    },
    {
      "author_name": "Rajesh Bhat",
      "author_url": "https://www.google.com/maps/contrib/100059225248246712757/reviews",
      "language": "en",
      "original_language": "en",
      "profile_photo_url": "https://lh3.googleusercontent.com/a-/ALV-UjXGhTtOMoz2jRuJCSt424NDsw5uRpCj2RSSVimrN0g9w0ipwpvP=s128-c0x00000000-cc-rp-mo-ba5",
      "rating": 4,
      "relative_time_description": "2 months ago",
      "text": "Food options are good, especially Indian vegetarian. The preparation & taste is excellent. Nice ambience except that the food court is non-aircon.",
      "time": 1740977846,
      "translated": false
    },
    {
      "author_name": "buyer n",
      "author_url": "https://www.google.com/maps/contrib/110286383647272032645/reviews",
      "language": "en",
      "original_language": "en",
      "profile_photo_url": "https://lh3.googleusercontent.com/a/ACg8ocIKVzR00zn0sPSeGhJhB2rwixNVGLTk207o62kqLyUptZdraA=s128-c0x00000000-cc-rp-mo-ba4",
      "rating": 2,
      "relative_time_description": "a year ago",
      "text": "They serve not fresh oily papadum. Briyani Mutton full of bones and fats",
      "time": 1709726532,
      "translated": false
    }
  ],
  "types": [
    "restaurant",
    "point_of_interest",
    "food",
    "establishment"
  ],
  "url": "https://maps.google.com/?cid=7767172188873185477",
  "user_ratings_total": 75,
  "vicinity": "30 Pioneer Crescent, West-park"
}