{
  "formatted_address": "245 Bishan Street 22, Singapore 570245",
  "geometry": {
    "location": {
      "lat": 1.3605524,
      "lng": 103.8439529
    },
    "viewport": {
      "northeast": {
        "lat": 1.361872480291502,
        "lng": 103.8453736802915
      },
      "southwest": {
        "lat": 1.359174519708498,
        "lng": 103.8426757197085
      }
    }
  },
  "name": "Bar 93 @ Horses’ Den",
  "place_id": "ChIJgXEK2TcX2jER-8N10uDaj7s",
  "rating": 5,
  "reviews": [
    {
      "author_name": "Rich Cogswell",
      "author_url": "https://www.google.com/maps/contrib/103943212674947648454/reviews",
      "language": "en",
      "original_language": "en",
      "profile_photo_url": "https://lh3.googleusercontent.com/a/ACg8ocJAJqjW7Yf1MtnFPBJkVyAJbXpwYiNbhrwVYNpNBJMOgXKvjw=s128-c0x00000000-cc-rp-mo",
      "rating": 5,
      "relative_time_description": "a year ago",
      "text": "An exceptional experience.\nI was lucky to be invited to savour this intimate no menu cocktail magic within a singular location.\nSpend a couple of hours in the company of a couple who’s passion is clean flavouring and unique combinations.\nStand outs? Chrysanthemum Negroni and Sakura Flower Martini - tired of the bar scenes? Beginner or connoisseur? No matter there’s joy for any visitor.",
      "time": 1699691470,
      "translated": false
    },
    {
      "author_name": "Desmond Wong",
      "author_url": "https://www.google.com/maps/contrib/114220117023892689160/reviews",
      "language": "en",
      "original_language": "en",
      "profile_photo_url": "https://lh3.googleusercontent.com/a-/ALV-UjVSDMvtwQXsjIZY6EO6IOYdgjdH0vEJ4JTH6bQq5VfCmHwW-Sk=s128-c0x00000000-cc-rp-mo-ba6",
      "rating": 5,
      "relative_time_description": "a year ago",
      "text": "A unique experience. My 1st visit to a house bar and this was very near my place. The place Joseph and Peiyi had qas nicely renovated to host guests. I had 3 cocktails, which are all different and tasted according to my request.  The 1st was a rough coffee and spicy, followed by a negroni and ended with a pi pa gao favoured cocktail. We also tried the beef steak and egg mago with bread. Hopefully, we get to come back again soon even though they have a long waitlist.",
      "time": 1685255763,
      "translated": false
    },
    {
      "author_name": "Woo Charlotte",
      "author_url": "https://www.google.com/maps/contrib/117845966920688990095/reviews",
      "language": "en",
      "original_language": "en",
      "profile_photo_url": "https://lh3.googleusercontent.com/a/ACg8ocIKpHSLj9XzanynRY_cF9I4mpsCmRRtf1Vi3rudIIgOLKt-Sg=s128-c0x00000000-cc-rp-mo",
      "rating": 5,
      "relative_time_description": "a year ago",
      "text": "The hosts are great and the cocktails are all one of a kind. Enjoy all the cocktails. Truly amazing 🤩\nI will come back again with my friends. Highly recommended",
      "time": 1716091050,
      "translated": false
    },
    {
      "author_name": "Tee Jin Hui",
      "author_url": "https://www.google.com/maps/contrib/111069063327196192456/reviews",
      "language": "en",
      "original_language": "en",
      "profile_photo_url": "https://lh3.googleusercontent.com/a/ACg8ocKIcNq05jARgzfbNgIS2m4TtEwl_Yk70vspG3clGxWcvrNo1A=s128-c0x00000000-cc-rp-mo",
      "rating": 5,
      "relative_time_description": "a year ago",
      "text": "Very difficult to get a spot as their slots are always filled. Put yourself on the waitlist and quickly respond once slots are open!! Had an opportunity recently and had a great night hosted by Joseph and Pei Yi. Their drinks were great and we loved almost every cocktail that was made.",
      "time": 1714733823,
      "translated": false
    },
    {
      "author_name": "J. Kang",
      "author_url": "https://www.google.com/maps/contrib/114762816041768658319/reviews",
      "language": "en",
      "original_language": "en",
      "profile_photo_url": "https://lh3.googleusercontent.com/a/ACg8ocI1VTqJ413xyV7RNIfhKN0VrXKTob3Giv_hVGciCFdwdMt83g=s128-c0x00000000-cc-rp-mo",
      "rating": 5,
      "relative_time_description": "a year ago",
      "text": "Never a dull moment here with Joseph and Peiyi. Ideal ratio doesn’t just apply to the drinks but also the good mix of guests we cross paths with. Oh also, count on Joseph to make you a Ramos Gin Fizz, he keeps it going with an undefeated face 😂",
      "time": 1716134538,
      "translated": false
    }
  ],
  "types": [
    "bar",
    "point_of_interest",
    "establishment"
  ],
  "url": "https://maps.google.com/?cid=13515261665900610555",
  "user_ratings_total": 104,
  "vicinity": "245 Bishan Street 22"
}