{
  "formatted_address": "Stadium Pl, #01-14 Kallang Wave Mall, 1, Singapore 397628",
  "geometry": {
    "location": {
      "lat": 1.3026967,
      "lng": 103.8730267
    },
    "viewport": {
      "northeast": {
        "lat": 1.303433680291502,
        "lng": 103.8750431802915
      },
      "southwest": {
        "lat": 1.300735719708498,
        "lng": 103.8723452197085
      }
    }
  },
  "name": "Good Cheer Stadium",
  "place_id": "ChIJZZ7n9ksY2jERoO4YO9o1iLE",
  "rating": 4,
  "reviews": [
    {
      "author_name": "Adam Chong",
      "author_url": "https://www.google.com/maps/contrib/113365685933101767623/reviews",
      "language": "en",
      "original_language": "en",
      "profile_photo_url": "https://lh3.googleusercontent.com/a/ACg8ocJCaqAwo_9tqemwFR2dfkQwj5qJrOjWAbjGbu7yVoFcZLtKqg=s128-c0x00000000-cc-rp-mo",
      "rating": 5,
      "relative_time_description": "a month ago",
      "text": "Customer service here is top notch. I dropped one of my earpieces at the bar, luckily managed to reach out to Esther via email even though it was after midnight. She was very fast in reaching out to the on-site staff who had already found my earpiece. Very happy customer, keep up the great service 👍",
      "time": 1743149629,
      "translated": false
    },
    {
      "author_name": "Dennis Chua",
      "author_url": "https://www.google.com/maps/contrib/110311363680451542230/reviews",
      "language": "en",
      "original_language": "en",
      "profile_photo_url": "https://lh3.googleusercontent.com/a/ACg8ocLu-BCVeB_PbmaoSU5hkwhIXPrJhTGxw80RPuKE2dVNrJXIZw=s128-c0x00000000-cc-rp-mo",
      "rating": 5,
      "relative_time_description": "2 months ago",
      "text": "Great place to have a couple of drinks, listening to music and play pool. On a gentle note, I think it's time for the pool table cloth to be changed. I can notice a few little holes on the pool cloth and wearing off at the cushions. Please kindly request your boss for a table cloth change if possible Esther (manager). 🙏🙏🙏. Will continue to support this great establishment.",
      "time": 1740558700,
      "translated": false
    },
    {
      "author_name": "T greensake",
      "author_url": "https://www.google.com/maps/contrib/102107525471936198024/reviews",
      "language": "en",
      "original_language": "en",
      "profile_photo_url": "https://lh3.googleusercontent.com/a/ACg8ocIZnv83PGhDQQ8QIfnt_ARJLi3OI_jhuI8AaxZ0AVYFHu9tcQ=s128-c0x00000000-cc-rp-mo-ba7",
      "rating": 4,
      "relative_time_description": "a year ago",
      "text": "Had Guinness Stout, Sapporo Premium Beer, Margherita Pizza & Sichuan Chicken this evening (11/10/23), was good. Music was loud due to karaoke singing by patrons.",
      "time": 1697123972,
      "translated": false
    },
    {
      "author_name": "Toemie Tan",
      "author_url": "https://www.google.com/maps/contrib/109281153021945724357/reviews",
      "language": "en",
      "original_language": "en",
      "profile_photo_url": "https://lh3.googleusercontent.com/a/ACg8ocKXHmtV67K6LHqLVMdaIodrJUstgNLQLXnT2TnBiClW0Qnb8A=s128-c0x00000000-cc-rp-mo",
      "rating": 1,
      "relative_time_description": "4 months ago",
      "text": "Staff notified us that there is no food about 11 when we walked in. That's fair. But more than an hour before closing, about 1230, everyone in the room can smell the aroma of air-fried food. After asking the staff, it's their \"staff snack\" before closing apparently?? If its so easy to just air fry some snacks, why couldn't you do it for paying customers?",
      "time": 1736615256,
      "translated": false
    },
    {
      "author_name": "Mark Tho",
      "author_url": "https://www.google.com/maps/contrib/108336947993231942478/reviews",
      "language": "en",
      "original_language": "en",
      "profile_photo_url": "https://lh3.googleusercontent.com/a-/ALV-UjXWTZXVH2Y7SxMXBXaOcENSUbEAqbxOlgrU8YOZm_59488SEU8OUg=s128-c0x00000000-cc-rp-mo-ba6",
      "rating": 4,
      "relative_time_description": "2 years ago",
      "text": "Nice place to hang out with darts, pool (free) and typical pub dice game. Also open karaoke - so expect some less desirable singing or songs! 😊\n\nDrinks at happy hour is cheap! Tower for $46! Bar food so so but for the entertainment this place offers, it’s acceptable.\n\nGreat hangout for big groups!",
      "time": 1680940642,
      "translated": false
    }
  ],
  "types": [
    "night_club",
    "bar",
    "point_of_interest",
    "establishment"
  ],
  "url": "https://maps.google.com/?cid=12792533952956526240",
  "user_ratings_total": 286,
  "vicinity": "Stadium Place, #01-14 Kallang Wave Mall, 1"
}