{
  "formatted_address": "91 Tanglin Rd, Singapore 247918",
  "geometry": {
    "location": {
      "lat": 1.3053255,
      "lng": 103.8250604
    },
    "viewport": {
      "northeast": {
        "lat": 1.306653130291502,
        "lng": 103.8262929802915
      },
      "southwest": {
        "lat": 1.303955169708498,
        "lng": 103.8235950197085
      }
    }
  },
  "name": "Tanglin Place",
  "place_id": "ChIJt10jr4sZ2jERo_UCZbIlPvE",
  "rating": 4,
  "reviews": [
    {
      "author_name": "Jerry Yao",
      "author_url": "https://www.google.com/maps/contrib/103362453297762486305/reviews",
      "language": "en",
      "original_language": "en",
      "profile_photo_url": "https://lh3.googleusercontent.com/a-/ALV-UjWTzIBjKtC_rvK8MXzFlW3NtDYGtMmv1DM4DK43BQ8Mjs7q9gHB=s128-c0x00000000-cc-rp-mo-ba5",
      "rating": 5,
      "relative_time_description": "2 months ago",
      "text": "Not a very fancy mall although the shops there trying to make them look fancy. They have a free toilet open to public on the ground floor, even if you are not a customer. So I have to leave a five star.",
      "time": 1741774220,
      "translated": false
    },
    {
      "author_name": "Chun Kiat Goh",
      "author_url": "https://www.google.com/maps/contrib/114063118057268311674/reviews",
      "language": "en",
      "original_language": "en",
      "profile_photo_url": "https://lh3.googleusercontent.com/a/ACg8ocIE6C3rSk4qfj6IKSllsp6KpiPSoSwmzHecob3_DDwJDsDKug=s128-c0x00000000-cc-rp-mo",
      "rating": 5,
      "relative_time_description": "a year ago",
      "text": "Great location. A better drop off point for those who have trouble getting about is in the carpark. Would be a lot better if you are coming here for your physiotherapy sessions!",
      "time": 1695360786,
      "translated": false
    },
    {
      "author_name": "Alice Chan",
      "author_url": "https://www.google.com/maps/contrib/100032078724241018161/reviews",
      "language": "en",
      "original_language": "en",
      "profile_photo_url": "https://lh3.googleusercontent.com/a/ACg8ocIoj7JuO29YtoMnGcATEO3hI4j_bVJ_-I-UfnIktegrB-5_-A=s128-c0x00000000-cc-rp-mo",
      "rating": 5,
      "relative_time_description": "a year ago",
      "text": "I come here for my physiotherapy on level 3. They are very skillful. Building is also nice and clean, with a lift that makes it easy for us to go up to the physio.",
      "time": 1695473545,
      "translated": false
    },
    {
      "author_name": "Eimear Mckernan",
      "author_url": "https://www.google.com/maps/contrib/113867636677081871081/reviews",
      "language": "en",
      "original_language": "en",
      "profile_photo_url": "https://lh3.googleusercontent.com/a/ACg8ocJfEvzDkvdDwbKl_hkVvvLUEwQt72VhHHBL-SwWWWkw6YaHeg=s128-c0x00000000-cc-rp-mo",
      "rating": 5,
      "relative_time_description": "9 months ago",
      "text": "there are some nice medical clinics and a lovely coffee shop on the ground floor. parking in the basement, very close to MRT",
      "time": 1723900350,
      "translated": false
    },
    {
      "author_name": "Weeszl lim",
      "author_url": "https://www.google.com/maps/contrib/114475314905996690995/reviews",
      "language": "en",
      "original_language": "en",
      "profile_photo_url": "https://lh3.googleusercontent.com/a/ACg8ocJSl0-OYOQbGBSK8TQDn8pOijdo6FT88AZmRi3rZkRnd-hngg=s128-c0x00000000-cc-rp-mo-ba3",
      "rating": 3,
      "relative_time_description": "2 years ago",
      "text": "Cafe and retail shop at level 1. Mostly offices, gym or clinic from level 2 till 4. The carpark access (tight car clearance space) cater for 10-12 cars maximum excl. handicapped lot (depending on the car size). Need to drive with care into the carpark (B2).",
      "time": 1679807912,
      "translated": false
    }
  ],
  "types": [
    "shopping_mall",
    "point_of_interest",
    "establishment"
  ],
  "url": "https://maps.google.com/?cid=17383373059825792419",
  "user_ratings_total": 78,
  "vicinity": "91 Tanglin Road"
}