{
  "formatted_address": "No. 65 Airport Blvd., Terminal 3 Arrival Hall North, Singapore 819663",
  "geometry": {
    "location": {
      "lat": 1.3555805,
      "lng": 103.9861962
    },
    "viewport": {
      "northeast": {
        "lat": 1.356526380291502,
        "lng": 103.9876359802915
      },
      "southwest": {
        "lat": 1.353828419708498,
        "lng": 103.9849380197085
      }
    }
  },
  "name": "UOB ATM - Changi Airport Terminal 3 - Arrival Hall North",
  "place_id": "ChIJQaOvMKA92jERHVbZjoYw5W8",
  "types": [
    "atm",
    "finance",
    "point_of_interest",
    "establishment"
  ],
  "url": "https://maps.google.com/?cid=8062904062357100061",
  "vicinity": "No. 65 Airport Boulevard, Terminal 3 Arrival Hall North"
}