{
  "formatted_address": "61, Block A3, Pusat Perdagangan Ion Medini, 3, Persiaran Medini Sentral 5, Bandar Medini Iskandar, 79600 Iskandar Puteri, Johor Darul Ta'zim, Malaysia",
  "geometry": {
    "location": {
      "lat": 1.4070857,
      "lng": 103.6198931
    },
    "viewport": {
      "northeast": {
        "lat": 1.408437930291502,
        "lng": 103.6212227802915
      },
      "southwest": {
        "lat": 1.405739969708498,
        "lng": 103.6185248197085
      }
    }
  },
  "name": "Wisma MyAngkasa Mukmin",
  "place_id": "ChIJRalT7xcL2jERH77SMSvTbJg",
  "types": [
    "insurance_agency",
    "point_of_interest",
    "establishment"
  ],
  "url": "https://maps.google.com/?cid=10983385773722746399",
  "vicinity": "61, Block A3, Pusat Perdagangan Ion Medini, 3, Persiaran Medini Sentral 5, Bandar Medini Iskandar, Iskandar Puteri"
}