{
  "formatted_address": "57 New Upper Changi Rd, Singapore 461057",
  "geometry": {
    "location": {
      "lat": 1.3238481,
      "lng": 103.9416387
    },
    "viewport": {
      "northeast": {
        "lat": 1.325303730291502,
        "lng": 103.9431008802915
      },
      "southwest": {
        "lat": 1.322605769708498,
        "lng": 103.9404029197085
      }
    }
  },
  "name": "兴隆潮州粥 Heng Long Teochew Porridge / Mixed Rice",
  "place_id": "ChIJ4dppIQAj2jERtTH52U522p0",
  "types": [
    "cafe",
    "food",
    "point_of_interest",
    "store",
    "establishment"
  ],
  "url": "https://maps.google.com/?cid=11374533889914122677",
  "vicinity": "57 New Upper Changi Road"
}